pcwa/__init__.py
pcwa/pcwa.py
pcwa-0.3.2.dist-info/METADATA
pcwa-0.3.2.dist-info/WHEEL
pcwa-0.3.2.dist-info/licenses/LICENSE
pcwa-0.3.2.dist-info/RECORD
