Metadata-Version: 2.1
Name: pcwa
Version: 0.3.2
Summary: A highly parallel and fast event detector based on CWT transform.
Project-URL: Homepage, https://github.com/vganjali/pcwa
Project-URL: Bug Tracker, https://github.com/vganjali/pcwa/issues
Author-email: Vahid Ganjalizadeh <vganjali@ucsc.edu>, Holger Schmidt <hschmidt@ucsc.edu>
License: MIT License
License-File: LICENSE
Classifier: License :: OSI Approved :: MIT License
Classifier: Operating System :: OS Independent
Classifier: Programming Language :: Python :: 3
Requires-Python: >=3.7
Requires-Dist: h5py>=2.10.0
Requires-Dist: matplotlib>=3.3.4
Requires-Dist: numpy>=1.19.2
Requires-Dist: pandas>=1.2.1
Requires-Dist: scipy>=1.6.2
